LICENSE
MANIFEST.in
README.md
setup.py
tap_twitter_ads/__init__.py
tap_twitter_ads/client.py
tap_twitter_ads/client_rest.py
tap_twitter_ads/discover.py
tap_twitter_ads/schema.py
tap_twitter_ads/streams.py
tap_twitter_ads/sync.py
tap_twitter_ads/transform.py
tap_twitter_ads.egg-info/PKG-INFO
tap_twitter_ads.egg-info/SOURCES.txt
tap_twitter_ads.egg-info/dependency_links.txt
tap_twitter_ads.egg-info/entry_points.txt
tap_twitter_ads.egg-info/requires.txt
tap_twitter_ads.egg-info/top_level.txt
tap_twitter_ads/schemas/account_media.json
tap_twitter_ads/schemas/accounts.json
tap_twitter_ads/schemas/advertiser_business_categories.json
tap_twitter_ads/schemas/campaigns.json
tap_twitter_ads/schemas/cards.json
tap_twitter_ads/schemas/cards_image_conversation.json
tap_twitter_ads/schemas/cards_poll.json
tap_twitter_ads/schemas/cards_video_conversation.json
tap_twitter_ads/schemas/content_categories.json
tap_twitter_ads/schemas/funding_instruments.json
tap_twitter_ads/schemas/iab_categories.json
tap_twitter_ads/schemas/line_item_apps.json
tap_twitter_ads/schemas/line_items.json
tap_twitter_ads/schemas/media_creatives.json
tap_twitter_ads/schemas/preroll_call_to_actions.json
tap_twitter_ads/schemas/promotable_users.json
tap_twitter_ads/schemas/promoted_accounts.json
tap_twitter_ads/schemas/promoted_tweets.json
tap_twitter_ads/schemas/scheduled_promoted_tweets.json
tap_twitter_ads/schemas/tailored_audiences.json
tap_twitter_ads/schemas/targeting_app_store_categories.json
tap_twitter_ads/schemas/targeting_conversations.json
tap_twitter_ads/schemas/targeting_criteria.json
tap_twitter_ads/schemas/targeting_devices.json
tap_twitter_ads/schemas/targeting_events.json
tap_twitter_ads/schemas/targeting_interests.json
tap_twitter_ads/schemas/targeting_languages.json
tap_twitter_ads/schemas/targeting_locations.json
tap_twitter_ads/schemas/targeting_network_operators.json
tap_twitter_ads/schemas/targeting_platform_versions.json
tap_twitter_ads/schemas/targeting_platforms.json
tap_twitter_ads/schemas/targeting_tv_markets.json
tap_twitter_ads/schemas/targeting_tv_shows.json
tap_twitter_ads/schemas/tracking_tags.json
tap_twitter_ads/schemas/tweets.json
tap_twitter_ads/schemas/shared/billing.json
