Metadata-Version: 2.1
Name: tap-twitter-ads
Version: 1.0.0
Summary: Singer.io tap for extracting data from the Twitter Ads API API
Home-page: UNKNOWN
Author: jeff.huth@bytecode.io
License: UNKNOWN
Platform: UNKNOWN
Classifier: Programming Language :: Python :: 3 :: Only
Provides-Extra: dev
